prosper_nn/__init__.py
prosper_nn/models/__init__.py
prosper_nn/models/autoencoder/__init__.py
prosper_nn/models/autoencoder/autoencoder.py
prosper_nn/models/autoencoder/autoencoder_ecnn_model.py
prosper_nn/models/crcnn/__init__.py
prosper_nn/models/crcnn/crcnn.py
prosper_nn/models/deep_feed_forward/__init__.py
prosper_nn/models/deep_feed_forward/deep_feed_forward.py
prosper_nn/models/dhcnn/__init__.py
prosper_nn/models/dhcnn/dhcnn.py
prosper_nn/models/ecnn/__init__.py
prosper_nn/models/ecnn/ecnn.py
prosper_nn/models/ecnn/ecnn_cell.py
prosper_nn/models/ecnn/gru_cell_variant.py
prosper_nn/models/ensemble/__init__.py
prosper_nn/models/ensemble/ensemble.py
prosper_nn/models/feedforward/__init__.py
prosper_nn/models/feedforward/feedforward.py
prosper_nn/models/fuzzy/Data_Intake.py
prosper_nn/models/fuzzy/__init__.py
prosper_nn/models/fuzzy/defuzzification.py
prosper_nn/models/fuzzy/frnn.py
prosper_nn/models/fuzzy/fuzzification.py
prosper_nn/models/fuzzy/fuzzy_inference.py
prosper_nn/models/fuzzy/membership_block.py
prosper_nn/models/fuzzy/membership_functions.py
prosper_nn/models/fuzzy/rule_manager.py
prosper_nn/models/hcnn/__init__.py
prosper_nn/models/hcnn/hcnn.py
prosper_nn/models/hcnn/hcnn_cell.py
prosper_nn/models/hcnn/hcnn_gru_cell.py
prosper_nn/models/hcnn_compressed/__init__.py
prosper_nn/models/hcnn_compressed/hcnn_cell_compressed.py
prosper_nn/models/hcnn_compressed/hcnn_compressed.py
prosper_nn/models/hcnn_known_u/__init__.py
prosper_nn/models/hcnn_known_u/hcnn_known_u.py
prosper_nn/models/hcnn_known_u/hcnn_known_u_cell.py
prosper_nn/utils/__init__.py
prosper_nn/utils/create_input_ecnn_hcnn.py
prosper_nn/utils/generate_time_series_data.py
prosper_nn/utils/neuron_correlation_hidden_layers.py
prosper_nn/utils/sensitivity_analysis.py
prosper_nn/utils/visualization.py
prosper_nn/utils/visualize_forecasts.py
tests/__init__.py
prosper_nn-0.3.2.dist-info/LICENSE
prosper_nn-0.3.2.dist-info/METADATA
prosper_nn-0.3.2.dist-info/WHEEL
prosper_nn-0.3.2.dist-info/top_level.txt
prosper_nn-0.3.2.dist-info/RECORD
