Metadata-Version: 2.1
Name: prosper-nn
Version: 0.3.2
Summary: Package contains, in PyTorch implemented, neural networks with problem specific pre-structuring architectures and utils that help building and understanding models.
Home-page: UNKNOWN
Author: Nico Beck, Julia Schemm
Author-email: nico.beck@iis.fraunhofer.de
License: UNKNOWN
Platform: UNKNOWN
Requires-Python: >=3.6
License-File: LICENSE
Requires-Dist: matplotlib<3.7,>=3.4.1
Requires-Dist: mypy>=0.782
Requires-Dist: numpy<2,>=1.20.2
Requires-Dist: pandas<2,>=1.1.2
Requires-Dist: scipy<2,>=1.5.0
Requires-Dist: seaborn<1,>=0.11.0
Requires-Dist: torch<3,>=1.6.0
